ollama_chat/__init__.py
ollama_chat/__main__.py
ollama_chat/app.py
ollama_chat/chat.py
ollama_chat/main.py
ollama_chat/ollama.py
ollama_chat/static/__init__.py
ollama_chat/static/index.html
ollama_chat/static/ollamaChat.bare
ollama_chat/static/ollamaChat.smd
ollama_chat/static/ollamaChatConversation.bare
ollama_chat/static/ollamaChatModels.bare
ollama_chat/static/ollamaChatTemplate.bare
ollama_chat-0.9.75.dist-info/licenses/LICENSE
ollama_chat-0.9.75.dist-info/METADATA
ollama_chat-0.9.75.dist-info/WHEEL
ollama_chat-0.9.75.dist-info/entry_points.txt
ollama_chat-0.9.75.dist-info/top_level.txt
ollama_chat-0.9.75.dist-info/RECORD
