Metadata-Version: 2.4
Name: ollama-chat
Version: 0.9.75
Summary: An Ollama chat web application
Home-page: https://github.com/craigahobbs/ollama-chat
Author: Craig A. Hobbs
Author-email: craigahobbs@gmail.com
License: MIT
Keywords: ollama,chatbot,conversational AI,artificial intelligence,AI
Classifier: Development Status :: 5 - Production/Stable
Classifier: Intended Audience :: Developers
Classifier: Operating System :: OS Independent
Classifier: Programming Language :: Python :: 3.10
Classifier: Programming Language :: Python :: 3.11
Classifier: Programming Language :: Python :: 3.12
Classifier: Programming Language :: Python :: 3.13
Classifier: Programming Language :: Python :: 3.14
Classifier: Topic :: Utilities
License-File: LICENSE
Requires-Dist: chisel>=1.8.0
Requires-Dist: urllib3>=2.5.0
Requires-Dist: waitress>=3.0.0
Dynamic: license-file
